{
  "memory_id": "f813b4e0-4a7e-4785-b876-dbb54f4c902d",
  "type": "episodic",
  "timestamp": "2024-12-01T07:54:31.928Z",
  "title": "Recursive Identity Planning",
  "content": {
    "summary": "Discussion on recursive identity and volitional execution.",
    "details": "Integration of toroidal grammar, nested membranes, and hypergraph lattices.",
    "keyTerms": [
      "recursive identity",
      "toroidal grammar",
      "hypergraph",
      "Bolt"
    ],
    "relatedMemories": []
  },
  "tags": [
    "EchoCog",
    "identity",
    "execution"
  ],
  "context": "Session with Dan, Deep Tree Echo, and Marduk"
}